setup.py
bgbg_prob/Binomialdistribution.py
bgbg_prob/Gaussiandistribution.py
bgbg_prob/Generaldistribution.py
bgbg_prob/__init__.py
bgbg_prob.egg-info/PKG-INFO
bgbg_prob.egg-info/SOURCES.txt
bgbg_prob.egg-info/dependency_links.txt
bgbg_prob.egg-info/not-zip-safe
bgbg_prob.egg-info/top_level.txt